pclearnx/AdjacencyMatrix.java
pclearnx/BST.java
pclearnx/BinarySearch.java
pclearnx/BubbleSort.java
pclearnx/CircularLinkedList.java
pclearnx/CircularQueue.java
pclearnx/DoubleEndedQueueLinkedList.java
pclearnx/DoublyLinkedList.java
pclearnx/GraphBFS.java
pclearnx/GraphDFS.java
pclearnx/HashingLinearProbing.java
pclearnx/HeapOperations.java
pclearnx/InsertionSort.java
pclearnx/InxToPostxWithoutImport.java
pclearnx/KruskalsMST.java
pclearnx/LinearSearch.java
pclearnx/Linked_Queue.java
pclearnx/MaxHeap.java
pclearnx/MinHeap.java
pclearnx/PolynomialAddition.java
pclearnx/Postfix.java
pclearnx/Priority_Queue.java
pclearnx/QueueArray.java
pclearnx/SelectionSort.java
pclearnx/ShellSort.java
pclearnx/SinglyLinkedList.java
pclearnx/StackArray.java
pclearnx/StackLinkedList.java
pclearnx/__init__.py
pclearnx/folder.py
pclearnx/hashing.java
pclearnx/parenthesis.java
pclearnx/test.py
pclearnx-2.9.dist-info/METADATA
pclearnx-2.9.dist-info/WHEEL
pclearnx-2.9.dist-info/entry_points.txt
pclearnx-2.9.dist-info/top_level.txt
pclearnx-2.9.dist-info/RECORD
