Metadata-Version: 2.4
Name: pclearnx
Version: 2.9
Summary: A package to create folders and copy predefined files
Author: jerrry
Author-email: jerry9333067@gmail.com
Classifier: Programming Language :: Python :: 3
Classifier: License :: OSI Approved :: MIT License
Classifier: Operating System :: OS Independent
Requires-Python: >=3.6
Dynamic: author
Dynamic: author-email
Dynamic: classifier
Dynamic: requires-python
Dynamic: summary
